ct_cloud_storage_mocker/__init__.py
ct_cloud_storage_mocker/_core.py
ct_cloud_storage_mocker/_core_test.py
ct_cloud_storage_mocker/_example_test.py
ct_cloud_storage_mocker/_version.py
ct_cloud_storage_mocker-0.1.5.dist-info/LICENSE
ct_cloud_storage_mocker-0.1.5.dist-info/METADATA
ct_cloud_storage_mocker-0.1.5.dist-info/WHEEL
ct_cloud_storage_mocker-0.1.5.dist-info/RECORD
