Metadata-Version: 2.3
Name: ct-cloud-storage-mocker
Version: 0.1.5
Summary: Mocker library of Google Cloud Storage with local filesystem mounting. Update for python3.13 compatibility
License: MIT
Keywords: cloud storage,gcloud,google,google cloud,storage
Author: Jim Robinson
Author-email: jim.robinson@croud.com
Requires-Python: >=3.8,<3.14
Classifier: License :: OSI Approved :: MIT License
Classifier: Programming Language :: Python :: 3.8
Classifier: Programming Language :: Python :: 3.9
Classifier: Programming Language :: Python :: 3.10
Classifier: Programming Language :: Python :: 3.11
Classifier: Programming Language :: Python :: 3.12
Requires-Dist: google-cloud-storage (>=2.7.0)
Project-URL: Bug Tracker, https://github.com/CroudTech/cloud-storage-mocker/issues
Project-URL: Homepage, https://github.com/CroudTech/cloud-storage-mocker
